aiotp/__init__.py
aiotp/typing.py
aiotp/abstracts/__init__.py
aiotp/abstracts/abstracts.py
aiotp/core/__init__.py
aiotp/core/otp.py
aiotp/hotp/__init__.py
aiotp/hotp/hotp.py
aiotp/sync/__init__.py
aiotp/sync/core/__init__.py
aiotp/sync/core/otp.py
aiotp/sync/hotp/__init__.py
aiotp/sync/hotp/hotp.py
aiotp/sync/totp/__init__.py
aiotp/sync/totp/totp.py
aiotp/sync/utils/__init__.py
aiotp/sync/utils/utils.py
aiotp/totp/__init__.py
aiotp/totp/totp.py
aiotp/utils/__init__.py
aiotp/utils/utils.py
aiotp-1.0.1.dist-info/LICENSE
aiotp-1.0.1.dist-info/METADATA
aiotp-1.0.1.dist-info/WHEEL
aiotp-1.0.1.dist-info/top_level.txt
aiotp-1.0.1.dist-info/RECORD
