Metadata-Version: 2.1
Name: aiotp
Version: 1.0.1
Summary: One-time password package in Python
Home-page: https://github.com/albu-org/aiotp
Author: albu
Author-email: albuorg@gmail.com
License: LGPLv3
Keywords: otp,totp,hotp,2FA,aiotp,one-time
Requires-Python: ~=3.7
License-File: LICENSE
